DSP.srcs/sources_1/new/DSP.v
`timescale 1ns / 1ps
//////////////////////////////////////////////////////////////////////////////////
// Company: 
// Engineer: 
// 
// Create Date: 31.07.2025 18:06:49
// Design Name: 
// Module Name: DSP
// Project Name: 
// Target Devices: 
// Tool Versions: 
// Description: 
// 
// Dependencies: 
// 
// Revision:
// Revision 0.01 - File Created
// Additional Comments:
// 
//////////////////////////////////////////////////////////////////////////////////
module DSP
#(parameter
A0REG =0,
A1REG =1, 
B0REG =0, 
B1REG =1,
CREG  =1, 
DREG  =1, 
MREG  =1, 
PREG  =1, 
CARRYINREG  =1, 
CARRYOUTREG =1,  
OPMODEREG   =1,
CARRYINSEL ="OPMODE5",// CARRYIN or OPMODE5
B_INPUT    ="DIRECT",//(attribute = DIRECT) or (attribute = CASCADE). 
RSTTYPE    ="SYNC"// ASYNC or SYNC
)
(
input[17:0] A,
input[17:0] B,
input[47:0] C,
input[17:0] D,
input CLK,
input CARRYIN,
input [7:0]OPMODE,
input[17:0] BCIN,
input RSTA,
input RSTB,
input RSTM,
input RSTP,
input RSTC,
input RSTD,
input RSTCARRYIN,
input RSTOPMODE,
input CEA,
input CEB,
input CEM,
input CEP,
input CEC,
input CED,
input CECARRYIN,
input CEOPMODE,
input[47:0] PCIN,
output [17:0] BCOUT,
output [47:0] PCOUT,
output [35:0] M,
output [47:0] P,
output CARRYOUT,
output CARRYOUTF
    );
    
    
  wire [7:0] OPMODE_reg;
    Reg_Wire_module #(.RW(OPMODEREG), .N(8), .RSTTYPE(RSTTYPE)) OPMODE_REG
      (.clk(CLK), .clk_en(CEOPMODE), .rst(RSTOPMODE),
       .d(OPMODE), .q(OPMODE_reg));
  
    ///////////////////////D
wire [17:0] D_reg;
Reg_Wire_module #(.RW(DREG),.N(18),.RSTTYPE(RSTTYPE)) D_REG 
 (.clk(CLK),.clk_en(CED),.rst(RSTD),.d(D),.q(D_reg)); 
 /////////////////////B
wire [17:0] B0_reg;
generate 
if(B_INPUT=="DIRECT") begin : B_direct
     Reg_Wire_module #(.RW(B0REG),.N(18),.RSTTYPE(RSTTYPE)) B0_REG 
       (.clk(CLK),.clk_en(CEB),.rst(RSTB),.d(B),.q(B0_reg));  
end
else begin : B_from_BCIN
     Reg_Wire_module #(.RW(B0REG),.N(18),.RSTTYPE(RSTTYPE)) B0_REG 
       (.clk(CLK),.clk_en(CEB),.rst(RSTB),.d(BCIN),.q(B0_reg));  
end
endgenerate
 
 /////////////////////A
wire [17:0] A0_reg;
Reg_Wire_module #(.RW(A0REG),.N(18),.RSTTYPE(RSTTYPE)) A0_REG 
  (.clk(CLK),.clk_en(CEA),.rst(RSTA),.d(A),.q(A0_reg));  
////////////////////C  
wire [47:0] C_reg;
  Reg_Wire_module #(.RW(CREG),.N(48),.RSTTYPE(RSTTYPE)) C_REG 
    (.clk(CLK),.clk_en(CEC),.rst(RSTC),.d(C),.q(C_reg));  
 ////////////////////////////////////////////////////////////////////////////// 
wire [17:0] DB_adder;   
assign DB_adder =(~OPMODE_reg[6])?(D_reg+B0_reg):(D_reg-B0_reg);
wire [17:0] MUX1_out; 
assign MUX1_out =(OPMODE_reg[4])?DB_adder:B0_reg;

wire [17:0] B1_reg;
Reg_Wire_module #(.RW(B1REG),.N(18),.RSTTYPE(RSTTYPE)) B1_REG 
      (.clk(CLK),.clk_en(CEB),.rst(RSTB),.d(MUX1_out),.q(B1_reg));
wire [17:0] A1_reg;
Reg_Wire_module #(.RW(A1REG),.N(18),.RSTTYPE(RSTTYPE)) A1_REG 
            (.clk(CLK),.clk_en(CEA),.rst(RSTA),.d(A0_reg),.q(A1_reg)); 
 ////////////////////////////////////////////////////////////////           
wire [35:0] A1_mul_B1 ;                   
assign A1_mul_B1 =A1_reg*B1_reg; 
  wire [35:0] M_reg;        
 Reg_Wire_module #(.RW(MREG),.N(36),.RSTTYPE(RSTTYPE)) M_REG 
            (.clk(CLK),.clk_en(CEM),.rst(RSTM),.d(A1_mul_B1),.q(M_reg)); 
  
  wire  CYI_reg;
           generate   
            if(CARRYINSEL=="OPMODE5") begin : OPMODE5
                 Reg_Wire_module #(.RW(CARRYINREG),.N(1),.RSTTYPE(RSTTYPE)) CYI_REG 
                   (.clk(CLK),.clk_en(CECARRYIN),.rst(RSTCARRYIN ),.d(OPMODE_reg[5]),.q(CYI_reg));  
            end
            else begin : CARRYIN_SEL 
                 Reg_Wire_module #(.RW(CARRYINREG),.N(1),.RSTTYPE(RSTTYPE)) CYI_REG 
                  (.clk(CLK),.clk_en(CECARRYIN),.rst(RSTCARRYIN ),.d(CARRYIN),.q(CYI_reg));  
            end
            endgenerate  
  
//////////////////////////////////////////////////////////
/////mux_x
  wire  [47:0]X_MUX; 
  MUX_4x1 #(.N(48)) X_mux_inst 
    (.in0({48'h0}),.in1({12'h0,M_reg}),.in2(P),.in3({D_reg[11:0],A1_reg[17:0],B1_reg[17:0]}),.sel(OPMODE_reg[1:0]),.out(X_MUX));
    

  /////mux_z
  wire  [47:0]Z_MUX; 
   MUX_4x1 #(.N(48)) Z_mux_inst 
     (.in0({48'h0}),.in1(PCIN),.in2(P),.in3(C_reg),.sel(OPMODE_reg[3:2]),.out(Z_MUX));
     
//assign Z_MUX= OPMODE[2]?(OPMODE[3]?C_reg:PCIN):(OPMODE[3]?P:{48'h0});
 //////////////////////////////////////////
wire  [48:0]XZ_adder;

assign XZ_adder= (~OPMODE_reg[7])?(X_MUX+Z_MUX+CYI_reg):Z_MUX-(X_MUX+CYI_reg);

Reg_Wire_module #(.RW(PREG),.N(48),.RSTTYPE(RSTTYPE)) P_REG 
 (.clk(CLK),.clk_en(CEP),.rst(RSTP),.d(XZ_adder[47:0]),.q(P));
  
 Reg_Wire_module #(.RW(CARRYOUTREG),.N(1),.RSTTYPE(RSTTYPE)) CYO_REG 
  (.clk(CLK),.clk_en(CECARRYIN),.rst(RSTCARRYIN ),.d(XZ_adder[48]),.q(CARRYOUT));  
  
  
 assign PCOUT =P;
 assign CARRYOUTF =CARRYOUT;
 assign BCOUT =B1_reg ;   
 assign M =M_reg;   
 
endmodule




module MUX_4x1 #(
    parameter N = 8  
)(
    input  [N-1:0] in0,
    input  [N-1:0] in1,
    input  [N-1:0] in2,
    input  [N-1:0] in3,
    input  [1:0] sel,
    output reg [N-1:0] out
);

    always @(*) begin
        case (sel)
            2'b00: out = in0;
            2'b01: out = in1;
            2'b10: out = in2;
            2'b11: out = in3;
            default: out = {N{1'b0}};
        endcase
    end

endmodule







module Reg_Wire_module
#(
    parameter RW = 1,                // 1: register, 0: wire
    parameter N = 10,
    parameter RSTTYPE = "SYNC"       // "ASYNC" or "SYNC"
)
(
    input clk,
    input clk_en,
    input rst,
    input [N-1:0] d,
    output reg [N-1:0] q
);

generate
    if (RW == 1) begin : reg_logic
        if (RSTTYPE == "ASYNC") begin : async_rst
            always @(posedge clk or posedge rst) begin
                if (rst)
                    q <= {N{1'b0}};
                else if(clk_en)
                    q <= d;
            end
        end else begin : sync_rst
            always @(posedge clk) begin
                if (rst)
                    q <= {N{1'b0}};
                else if(clk_en)
                    q <= d;
            end
        end
    end else begin : wire_logic
        always @(*) begin
            q = d;
        end
    end
endgenerate

endmodule

DSP.srcs/sim_1/new/tb_DSP.v
`timescale 1ns / 1ps
//////////////////////////////////////////////////////////////////////////////////
// Testbench for DSP48A1-style “DSP” module
// Exercises reset plus four dynamic OPMODE paths with self-checking.
//===============================================================================
module tb_DSP;

  // Clock & Reset
  reg         CLK;             // 100 MHz clock
  reg         rst;             // global synchronous reset

  // DUT inputs
  reg  [17:0] A, B, D;         // data inputs
  reg  [47:0] C;               // wide C-port input
  reg  [17:0] BCIN;            // cascade B input
  reg  [47:0] PCIN;            // cascade P input
  reg         CARRYIN;         // carry-in bit
  reg  [7:0]  OPMODE;          // dynamic function control

  // DUT outputs
  wire [17:0] BCOUT;           // cascade B output
  wire [35:0] M;               // multiplier output
  wire [47:0] P, PCOUT;        // accumulator outputs
  wire        CARRYOUT;        // adjacent-slice carry
  wire        CARRYOUTF;       // fabric carry

  // All CE & RST signals tied to rst/1 unless overridden
  wire RSTA       = rst,
       RSTB       = rst,
       RSTM       = rst,
       RSTP       = rst,
       RSTC       = rst,
       RSTD       = rst,
       RSTCARRYIN = rst,
       RSTOPMODE  = rst;

  wire CEA        = 1'b1,
       CEB        = 1'b1,
       CEM        = 1'b1,
       CEP        = 1'b1,
       CEC        = 1'b1,
       CED        = 1'b1,
       CECARRYIN  = 1'b1,
       CEOPMODE   = 1'b1;

  // Instantiate the DUT with default parameters
  DSP dut (
    .A           (A),
    .B           (B),
    .C           (C),
    .D           (D),
    .CLK         (CLK),
    .CARRYIN     (CARRYIN),
    .OPMODE      (OPMODE),
    .BCIN        (BCIN),
    .RSTA        (RSTA),
    .RSTB        (RSTB),
    .RSTM        (RSTM),
    .RSTP        (RSTP),
    .RSTC        (RSTC),
    .RSTD        (RSTD),
    .RSTCARRYIN  (RSTCARRYIN),
    .RSTOPMODE   (RSTOPMODE),
    .CEA         (CEA),
    .CEB         (CEB),
    .CEM         (CEM),
    .CEP         (CEP),
    .CEC         (CEC),
    .CED         (CED),
    .CECARRYIN   (CECARRYIN),
    .CEOPMODE    (CEOPMODE),
    .PCIN        (PCIN),
    .BCOUT       (BCOUT),
    .PCOUT       (PCOUT),
    .M           (M),
    .P           (P),
    .CARRYOUT    (CARRYOUT),
    .CARRYOUTF   (CARRYOUTF)
  );

  // Clock generator: toggle every 5 ns ? 100 MHz
  initial begin
    CLK = 0;
    forever #5 CLK = ~CLK;
  end

reg [47:0] prevP; reg prevC;
  // Waveform dump
  initial begin
    $dumpfile("tb_DSP.vcd");
    $dumpvars(0, tb_DSP);
  end
//------------------------------------------------------------------------
    // 2. Stimulus & Self-Checking
    //------------------------------------------------------------------------
    initial begin
      // ------------------------------------------------------------
      // 2.1 Reset verification
      // ------------------------------------------------------------
      rst      = 1;                  // assert reset high
      // drive all inputs to random / nonzero
      A        = 18'h3A5;
      B        = 18'h1C2;
      C        = 48'h1234_5678_ABCD;
      D        = 18'h0F0;
      BCIN     = 18'h055;
      PCIN     = 48'h00FF_FF00;
      CARRYIN  = 1'b1;
      OPMODE   = 8'hFF;
      // wait one falling edge to sample outputs under reset
      @(negedge CLK);
      @(negedge CLK);
      @(negedge CLK);
      @(negedge CLK);
      @(negedge CLK);
      // check that all outputs are zero
      if (BCOUT !== 0 || M !== 0 || P !== 0 || PCOUT !== 0 ||
          CARRYOUT !== 0 || CARRYOUTF !== 0)
        $display("ERROR: Reset failed at time %0t", $time);
      else
        $display("PASS: Reset cleared outputs at time %0t", $time);
  
      rst = 0;                       // deassert reset
      @(posedge CLK);                // align to a clock
      // ------------------------------------------------------------
          // 2.2 DSP Path 1: pre-subtract, multiply, post-add accumulate
          // OPMODE = 8'b1101_1101
          // D-B ? *A ? +C
          // Expected BCOUT=0x0F, M=0x12C, P=PCOUT=0x32, CARRYOUT=0
          // ------------------------------------------------------------
        OPMODE   = 8'b1101_1101;
          A        = 18'd20;
          B        = 18'd10;
          C        = 48'd350;
          D        = 18'd25;
            BCIN     = $random ;
            PCIN     = $random;
            CARRYIN  = $random ;
          repeat (4) @(negedge CLK);     // wait 4 pipeline stages
       
          $display("---- Path 1 Results ----");
          if (BCOUT !== 18'h0F)       $display("FAIL1: BCOUT=%h", BCOUT); else $display("PASS1: BCOUT");
          if (M     !== 36'h12C)       $display("FAIL1: M=%h", M);       else $display("PASS1: M");
          if (P     !== 48'h032)       $display("FAIL1: P=%h", P);       else $display("PASS1: P");
          if (PCOUT !== 48'h032)       $display("FAIL1: PCOUT=%h", PCOUT); else $display("PASS1: PCOUT");
          if ({CARRYOUT,CARRYOUTF} !== 2'b00) $display("FAIL1: CARRY=%b/%b", CARRYOUT, CARRYOUTF);
          else                                $display("PASS1: CARRY");
          
         // ------------------------------------------------------------
              // 2.3 DSP Path 2: pre-add, multiply, no post accumulation
              // OPMODE = 8'b0001_0000
              // D+B ? *A, P=0
              // Expected BCOUT=0x23, M=0x2BC, P/PCOUT=0, CARRY=0
              // ------------------------------------------------------------
              OPMODE   = 8'b0001_0000;
              A        = 18'd20;
              B        = 18'd10;
              C        = 48'd350;
              D        = 18'd25;
                     BCIN     = $random ;
                     PCIN     = $random;
                     CARRYIN  = $random ;
              repeat (3) @(negedge CLK);     // 3-stage longest path
          
              $display("---- Path 2 Results ----");
              if (BCOUT !== 18'h023)       $display("FAIL2: BCOUT=%h", BCOUT); else $display("PASS2: BCOUT");
              if (M     !== 36'h2BC)       $display("FAIL2: M=%h", M);       else $display("PASS2: M");
              if ({P,PCOUT} !== {48'h0,48'h0}) $display("FAIL2: P/PCOUT=%h/%h", P, PCOUT);
              else                            $display("PASS2: P/PCOUT");
              if ({CARRYOUT,CARRYOUTF} !== 2'b00) $display("FAIL2: CARRY=%b/%b", CARRYOUT, CARRYOUTF);
              else                                  $display("PASS2: CARRY");
              
        // ------------------------------------------------------------
                  // 2.4 DSP Path 3: no pre, P-feedback through X & Z
                  // OPMODE = 8'b0000_1010
                  // BCOUT=B, M=A*B, P & CARRY hold previous values
                  // ------------------------------------------------------------
                  // Capture previous P & carry                  
                  prevP    = P; prevC = CARRYOUT;
                  OPMODE   = 8'b0000_1010;
                  A        = 18'd20;
                  B        = 18'd10;
                  C        = 48'd350;
                  D        = 18'd25;
                 BCIN     = $random ;
                  PCIN     = $random;
                CARRYIN  = $random ;
                  repeat (3) @(negedge CLK);
              
                  $display("---- Path 3 Results ----");
                  if (BCOUT !== 18'h00A)       $display("FAIL3: BCOUT=%h", BCOUT); else $display("PASS3: BCOUT");
                  if (M     !== 36'h0C8)       $display("FAIL3: M=%h", M);       else $display("PASS3: M");
                  if ({P,PCOUT} !== {prevP,prevP}) $display("FAIL3: P/PCOUT=%h/%h", P, PCOUT);
                  else                             $display("PASS3: P/PCOUT");
                  if ({CARRYOUT,CARRYOUTF} !== {prevC,prevC}) $display("FAIL3: CARRY=%b/%b", CARRYOUT, CARRYOUTF);
                  else                                         $display("PASS3: CARRY");      
      // ------------------------------------------------------------
                      // 2.5 DSP Path 4: no pre, post-subtract with concat X & PCIN Z
                      // OPMODE = 8'b1010_0111
                      // X = {D[11:0],A,B}; Z=PCIN; P=Z-(X+CIN)
                      // Expected BCOUT=0x6, M=0x1E, P/PCOUT=0xFE6FFFEC0BB1, CARRY=1
                      // ------------------------------------------------------------
                      OPMODE   = 8'b1010_0111;
                      A        = 18'd5;
                      B        = 18'd6;
                      C        = 48'd350;     // unused
                      D        = 18'd25;
                      PCIN     = 48'd3000 ;
                       BCIN     = $random;
                      CARRYIN  = $random ;
                      repeat (3) @(negedge CLK);
                  
                      $display("---- Path 4 Results ----");
                      if (BCOUT !== 18'h006)       $display("FAIL4: BCOUT=%h", BCOUT); else $display("PASS4: BCOUT");
                      if (M     !== 36'h01E)       $display("FAIL4: M=%h", M);       else $display("PASS4: M");
                      if ({P,PCOUT} !== {48'hFE6FFFEC0BB1, 48'hFE6FFFEC0BB1})
                        $display("FAIL4: P/PCOUT=%h/%h", P, PCOUT);
                      else
                        $display("PASS4: P/PCOUT");
                      if ({CARRYOUT,CARRYOUTF} !== 2'b11)
                        $display("FAIL4: CARRY=%b/%b", CARRYOUT, CARRYOUTF);
                      else
                        $display("PASS4: CARRY");
                  
                      $display("All tests completed at time %0t", $time);
                      #20;        
               
          
   $stop;
   end   


endmodule

DSP.sim/sim_1/behav/xsim/tb_DSP.vcd
$date
   Sun Aug  3 19:54:08 2025
$end
$version
  2018.2
$end
$timescale
  1ps
$end
$scope module tb_DSP $end
$var reg 1 ! CLK $end
$var reg 1 " rst $end
$var reg 18 # A [17:0] $end
$var reg 18 $ B [17:0] $end
$var reg 18 % D [17:0] $end
$var reg 48 & C [47:0] $end
$var reg 18 ' BCIN [17:0] $end
$var reg 48 ( PCIN [47:0] $end
$var reg 1 ) CARRYIN $end
$var reg 8 * OPMODE [7:0] $end
$var wire 18 + BCOUT [17:0] $end
$var wire 36 , M [35:0] $end
$var wire 48 - P [47:0] $end
$var wire 48 . PCOUT [47:0] $end
$var wire 1 / CARRYOUT $end
$var wire 1 0 CARRYOUTF $end
$var wire 1 1 RSTA $end
$var wire 1 2 RSTB $end
$var wire 1 3 RSTM $end
$var wire 1 4 RSTP $end
$var wire 1 5 RSTC $end
$var wire 1 6 RSTD $end
$var wire 1 7 RSTCARRYIN $end
$var wire 1 8 RSTOPMODE $end
$var wire 1 9 CEA $end
$var wire 1 : CEB $end
$var wire 1 ; CEM $end
$var wire 1 < CEP $end
$var wire 1 = CEC $end
$var wire 1 > CED $end
$var wire 1 ? CECARRYIN $end
$var wire 1 @ CEOPMODE $end
$var reg 48 A prevP [47:0] $end
$var reg 1 B prevC $end
$scope module dut $end
$var wire 18 C A [17:0] $end
$var wire 18 D B [17:0] $end
$var wire 48 E C [47:0] $end
$var wire 18 F D [17:0] $end
$var wire 1 G CLK $end
$var wire 1 H CARRYIN $end
$var wire 8 I OPMODE [7:0] $end
$var wire 18 J BCIN [17:0] $end
$var wire 1 1 RSTA $end
$var wire 1 2 RSTB $end
$var wire 1 3 RSTM $end
$var wire 1 4 RSTP $end
$var wire 1 5 RSTC $end
$var wire 1 6 RSTD $end
$var wire 1 7 RSTCARRYIN $end
$var wire 1 8 RSTOPMODE $end
$var wire 1 9 CEA $end
$var wire 1 : CEB $end
$var wire 1 ; CEM $end
$var wire 1 < CEP $end
$var wire 1 = CEC $end
$var wire 1 > CED $end
$var wire 1 ? CECARRYIN $end
$var wire 1 @ CEOPMODE $end
$var wire 48 K PCIN [47:0] $end
$var wire 18 + BCOUT [17:0] $end
$var wire 48 . PCOUT [47:0] $end
$var wire 36 , M [35:0] $end
$var wire 48 - P [47:0] $end
$var wire 1 / CARRYOUT $end
$var wire 1 0 CARRYOUTF $end
$var wire 8 L OPMODE_reg [7:0] $end
$var wire 18 M D_reg [17:0] $end
$var wire 18 N B0_reg [17:0] $end
$var wire 18 O A0_reg [17:0] $end
$var wire 48 P C_reg [47:0] $end
$var wire 18 Q DB_adder [17:0] $end
$var wire 18 R MUX1_out [17:0] $end
$var wire 18 S B1_reg [17:0] $end
$var wire 18 T A1_reg [17:0] $end
$var wire 36 U A1_mul_B1 [35:0] $end
$var wire 36 V M_reg [35:0] $end
$var wire 1 W CYI_reg $end
$var wire 48 X X_MUX [47:0] $end
$var wire 48 Y Z_MUX [47:0] $end
$var wire 49 Z XZ_adder [48:0] $end
$var parameter 32 [ A0REG [31:0] $end
$var parameter 32 \ A1REG [31:0] $end
$var parameter 32 ] B0REG [31:0] $end
$var parameter 32 ^ B1REG [31:0] $end
$var parameter 32 _ CREG [31:0] $end
$var parameter 32 ` DREG [31:0] $end
$var parameter 32 a MREG [31:0] $end
$var parameter 32 b PREG [31:0] $end
$var parameter 32 c CARRYINREG [31:0] $end
$var parameter 32 d CARRYOUTREG [31:0] $end
$var parameter 32 e OPMODEREG [31:0] $end
$var parameter 56 f CARRYINSEL [55:0] $end
$var parameter 48 g B_INPUT [47:0] $end
$var parameter 32 h RSTTYPE [31:0] $end
$scope module OPMODE_REG $end
$var wire 1 G clk $end
$var wire 1 @ clk_en $end
$var wire 1 8 rst $end
$var wire 8 I d [7:0] $end
$var reg 8 i q [7:0] $end
$var parameter 32 j RW [31:0] $end
$var parameter 32 k N [31:0] $end
$var parameter 32 l RSTTYPE [31:0] $end
$upscope $end
$scope module D_REG $end
$var wire 1 G clk $end
$var wire 1 > clk_en $end
$var wire 1 6 rst $end
$var wire 18 F d [17:0] $end
$var reg 18 m q [17:0] $end
$var parameter 32 n RW [31:0] $end
$var parameter 32 o N [31:0] $end
$var parameter 32 p RSTTYPE [31:0] $end
$upscope $end
$scope module B_direct.B0_REG $end
$var wire 1 G clk $end
$var wire 1 : clk_en $end
$var wire 1 2 rst $end
$var wire 18 D d [17:0] $end
$var reg 18 q q [17:0] $end
$var parameter 32 r RW [31:0] $end
$var parameter 32 s N [31:0] $end
$var parameter 32 t RSTTYPE [31:0] $end
$upscope $end
$scope module A0_REG $end
$var wire 1 G clk $end
$var wire 1 9 clk_en $end
$var wire 1 1 rst $end
$var wire 18 C d [17:0] $end
$var reg 18 u q [17:0] $end
$var parameter 32 v RW [31:0] $end
$var parameter 32 w N [31:0] $end
$var parameter 32 x RSTTYPE [31:0] $end
$upscope $end
$scope module C_REG $end
$var wire 1 G clk $end
$var wire 1 = clk_en $end
$var wire 1 5 rst $end
$var wire 48 E d [47:0] $end
$var reg 48 y q [47:0] $end
$var parameter 32 z RW [31:0] $end
$var parameter 32 { N [31:0] $end
$var parameter 32 | RSTTYPE [31:0] $end
$upscope $end
$scope module B1_REG $end
$var wire 1 G clk $end
$var wire 1 : clk_en $end
$var wire 1 2 rst $end
$var wire 18 R d [17:0] $end
$var reg 18 } q [17:0] $end
$var parameter 32 ~ RW [31:0] $end
$var parameter 32 !! N [31:0] $end
$var parameter 32 "! RSTTYPE [31:0] $end
$upscope $end
$scope module A1_REG $end
$var wire 1 G clk $end
$var wire 1 9 clk_en $end
$var wire 1 1 rst $end
$var wire 18 O d [17:0] $end
$var reg 18 #! q [17:0] $end
$var parameter 32 $! RW [31:0] $end
$var parameter 32 %! N [31:0] $end
$var parameter 32 &! RSTTYPE [31:0] $end
$upscope $end
$scope module M_REG $end
$var wire 1 G clk $end
$var wire 1 ; clk_en $end
$var wire 1 3 rst $end
$var wire 36 U d [35:0] $end
$var reg 36 '! q [35:0] $end
$var parameter 32 (! RW [31:0] $end
$var parameter 32 )! N [31:0] $end
$var parameter 32 *! RSTTYPE [31:0] $end
$upscope $end
$scope module OPMODE5.CYI_REG $end
$var wire 1 G clk $end
$var wire 1 ? clk_en $end
$var wire 1 7 rst $end
$var wire 1 +! d [0:0] $end
$var reg 1 ,! q [0:0] $end
$var parameter 32 -! RW [31:0] $end
$var parameter 32 .! N [31:0] $end
$var parameter 32 /! RSTTYPE [31:0] $end
$upscope $end
$scope module X_mux_inst $end
$var wire 48 0! in0 [47:0] $end
$var wire 48 1! in1 [47:0] $end
$var wire 48 - in2 [47:0] $end
$var wire 48 2! in3 [47:0] $end
$var wire 2 3! sel [1:0] $end
$var reg 48 4! out [47:0] $end
$var parameter 32 5! N [31:0] $end
$upscope $end
$scope module Z_mux_inst $end
$var wire 48 6! in0 [47:0] $end
$var wire 48 K in1 [47:0] $end
$var wire 48 - in2 [47:0] $end
$var wire 48 P in3 [47:0] $end
$var wire 2 7! sel [1:0] $end
$var reg 48 8! out [47:0] $end
$var parameter 32 9! N [31:0] $end
$upscope $end
$scope module P_REG $end
$var wire 1 G clk $end
$var wire 1 < clk_en $end
$var wire 1 4 rst $end
$var wire 48 :! d [47:0] $end
$var reg 48 ;! q [47:0] $end
$var parameter 32 <! RW [31:0] $end
$var parameter 32 =! N [31:0] $end
$var parameter 32 >! RSTTYPE [31:0] $end
$upscope $end
$scope module CYO_REG $end
$var wire 1 G clk $end
$var wire 1 ? clk_en $end
$var wire 1 7 rst $end
$var wire 1 ?! d [0:0] $end
$var reg 1 @! q [0:0] $end
$var parameter 32 A! RW [31:0] $end
$var parameter 32 B! N [31:0] $end
$var parameter 32 C! RSTTYPE [31:0] $end
$upscope $end
$upscope $end
$upscope $end
$enddefinitions $end
#0
$dumpvars
0!
b10010 !!
1"
b1010011010110010100111001000011 "!
b1110100101 #
bx #!
b111000010 $
b1 $!
b11110000 %
b10010 %!
b100100011010001010110011110001010101111001101 &
b1010011010110010100111001000011 &!
b1010101 '
bx '!
b111111111111111100000000 (
b1 (!
1)
b100100 )!
b11111111 *
b1010011010110010100111001000011 *!
bx +
x+!
bx ,
x,!
bx -
b1 -!
bx .
b1 .!
x/
b1010011010110010100111001000011 /!
x0
b0 0!
11
b0xxxxxxxxxxxxxxxxxxxxxxxxxxxxxxxxxxxx 1!
12
bx 2!
13
bx 3!
14
b0 4!
15
b110000 5!
16
b0 6!
17
bx 7!
18
b0 8!
19
b110000 9!
1:
bx :!
1;
bx ;!
1<
b1 <!
1=
b110000 =!
1>
b1010011010110010100111001000011 >!
1?
x?!
1@
x@!
bx A
b1 A!
xB
b1 B!
b1110100101 C
b1010011010110010100111001000011 C!
b111000010 D
b100100011010001010110011110001010101111001101 E
b11110000 F
0G
1H
b11111111 I
b1010101 J
b111111111111111100000000 K
bx L
bx M
b111000010 N
b1110100101 O
bx P
bx Q
bx R
bx S
bx T
bx U
bx V
xW
b0 X
b0 Y
bx Z
b0 [
b1 \
b0 ]
b1 ^
b1 _
b1 `
b1 a
b1 b
b1 c
b1 d
b1 e
b1001111010100000100110101001111010001000100010100110101 f
b10001000100100101010010010001010100001101010100 g
b1010011010110010100111001000011 h
bx i
b1 j
b1000 k
b1010011010110010100111001000011 l
bx m
b1 n
b10010 o
b1010011010110010100111001000011 p
b111000010 q
b0 r
b10010 s
b1010011010110010100111001000011 t
b1110100101 u
b0 v
b10010 w
b1010011010110010100111001000011 x
bx y
b1 z
b110000 {
b1010011010110010100111001000011 |
bx }
b1 ~
$end
#5000
1!
b0 #!
b0 '!
b0 +
0+!
b0 ,
0,!
b0 -
b0 .
0/
00
b0 1!
b0 2!
b0 3!
b0 4!
b0 7!
b0 8!
b0 :!
b0 ;!
0?!
0@!
1G
b0 L
b0 M
b0 P
b111000010 Q
b111000010 R
b0 S
b0 T
b0 U
b0 V
0W
b0 Z
b0 i
b0 m
b0 y
b0 }
#10000
0!
0G
#15000
1!
1G
#20000
0!
0G
#25000
1!
1G
#30000
0!
0G
#35000
1!
1G
#40000
0!
0G
#45000
1!
1G
#50000
0!
0"
01
02
03
04
05
06
07
08
0G
#55000
1!
b10100 #
b1110100101 #!
b1010 $
b11001 %
b101011110 &
b10011010100100100 '
b111111111111111111000000100010010101111010000001 (
1)
b11011101 *
b111000010 +
0+!
b11001000000001110100101000000000111000010 2!
b1 3!
b0 4!
b11 7!
b101011110 8!
b101011110 :!
0?!
b10100 C
b1010 D
b101011110 E
b11001 F
1G
b11011101 I
b10011010100100100 J
b111111111111111111000000100010010101111010000001 K
b11011101 L
b11001 M
b1010 N
b10100 O
b101011110 P
b1111 Q
b1111 R
b111000010 S
b1110100101 T
b1100110100000001010 U
b101011110 Y
b101011110 Z
b11011101 i
b11001 m
b1010 q
b10100 u
b101011110 y
b111000010 }
#60000
0!
0G
#65000
1!
b10100 #!
b1100110100000001010 '!
b1111 +
b1100110100000001010 ,
b101011110 -
b101011110 .
b1100110100000001010 1!
b11001000000000000010100000000000000001111 2!
b1100110100000001010 4!
b101011110 8!
b111111111111111111111111111110011001100101010100 :!
b101011110 ;!
1?!
1G
b1111 S
b10100 T
b100101100 U
b1100110100000001010 V
b1100110100000001010 X
b1111111111111111111111111111110011001100101010100 Z
b1111 }
#70000
0!
0G
#75000
1!
b100101100 '!
b100101100 ,
b111111111111111111111111111110011001100101010100 -
b111111111111111111111111111110011001100101010100 .
1/
10
b100101100 1!
b100101100 4!
b101011110 8!
b110010 :!
b111111111111111111111111111110011001100101010100 ;!
0?!
1@!
1G
b100101100 V
b100101100 X
b110010 Z
#80000
0!
0G
#85000
1!
b110010 -
b110010 .
0/
00
b100101100 4!
b101011110 8!
b110010 ;!
0@!
1G
#90000
0!
b10100 #
b1010 $
b11001 %
b101011110 &
b101011001100011 '
b110101110010111101100001101 (
1)
b10000 *
b101011110 8!
0G
b10000 I
b101011001100011 J
b110101110010111101100001101 K
#95000
1!
0+!
b0 3!
b0 4!
b0 7!
b0 8!
b0 :!
0?!
1G
b10000 L
b100011 Q
b100011 R
b0 X
b0 Y
b0 Z
b10000 i
#100000
0!
0G
#105000
1!
b100011 +
b0 -
b0 .
b11001000000000000010100000000000000100011 2!
b0 4!
b0 8!
b0 ;!
1G
b100011 S
b1010111100 U
b100011 }
#110000
0!
0G
#115000
1!
b1010111100 '!
b1010111100 ,
b1010111100 1!
b0 4!
1G
b1010111100 V
#120000
0!
b10100 #
b1010 $
b11001 %
b101011110 &
b101000010001100101 '
b111111111111111110001001001101110101001000010010 (
1)
b1010 *
b0 8!
b0 A
0B
0G
b1010 I
b101000010001100101 J
b111111111111111110001001001101110101001000010010 K
#125000
1!
0+!
b10 3!
b0 4!
b10 7!
b0 8!
1G
b1010 L
b1010 R
b1010 i
#130000
0!
0G
#135000
1!
b1010 +
b11001000000000000010100000000000000001010 2!
b0 4!
1G
b1010 S
b11001000 U
b1010 }
#140000
0!
0G
#145000
1!
b11001000 '!
b11001000 ,
b11001000 1!
b0 4!
1G
b11001000 V
#150000
0!
b101 #
b110 $
b11001 %
b101011110 &
b111100110100001101 '
b101110111000 (
0)
b10100111 *
b0 8!
b101 C
b110 D
0G
0H
b10100111 I
b111100110100001101 J
b101110111000 K
b110 N
b101 O
b11111 Q
b110 R
b110 q
b101 u
#155000
1!
b101 #!
b110 +
1+!
b11001000000000000000101000000000000000110 2!
b11 3!
b11001000000000000000101000000000000000110 4!
b1 7!
b101110111000 8!
b111111100110111111111111111011000000101110110010 :!
1?!
1G
b10100111 L
b110 S
b101 T
b11110 U
b11001000000000000000101000000000000000110 X
b101110111000 Y
b1111111100110111111111111111011000000101110110010 Z
b10100111 i
b110 }
#160000
0!
0G
#165000
1!
b11110 '!
b11110 ,
1,!
b111111100110111111111111111011000000101110110010 -
b111111100110111111111111111011000000101110110010 .
1/
10
b11110 1!
b11001000000000000000101000000000000000110 4!
b101110111000 8!
b111111100110111111111111111011000000101110110001 :!
b111111100110111111111111111011000000101110110010 ;!
1?!
1@!
1G
b11110 V
1W
b1111111100110111111111111111011000000101110110001 Z
#170000
0!
0G
